ignition/__init__.py
ignition/pkg_info.json
ignition/api/exceptions.py
ignition/boot/__init__.py
ignition/boot/api.py
ignition/boot/app.py
ignition/boot/config.py
ignition/boot/connexionutils.py
ignition/boot/configurators/jobqueue.py
ignition/boot/configurators/management.py
ignition/boot/configurators/messaging.py
ignition/boot/configurators/movedapis.py
ignition/boot/configurators/progress_events.py
ignition/boot/configurators/requestqueue.py
ignition/boot/configurators/resourcedriverapi.py
ignition/boot/configurators/templating.py
ignition/boot/configurators/utils.py
ignition/cli/__init__.py
ignition/cli/cmd_create.py
ignition/cli/cmd_testdrive.py
ignition/cli/entry.py
ignition/locations/__init__.py
ignition/locations/exceptions.py
ignition/locations/kubernetes.py
ignition/locations/utils.py
ignition/model/associated_topology.py
ignition/model/failure.py
ignition/model/lifecycle.py
ignition/model/progress_events.py
ignition/model/references.py
ignition/openapi/__init__.py
ignition/openapi/management.yaml
ignition/openapi/moved-infrastructure.yaml
ignition/openapi/moved-lifecycle.yaml
ignition/openapi/resource-driver.yaml
ignition/service/__init__.py
ignition/service/api.py
ignition/service/config.py
ignition/service/framework.py
ignition/service/health.py
ignition/service/logging.py
ignition/service/management.py
ignition/service/messaging.py
ignition/service/progress_events.py
ignition/service/queue.py
ignition/service/requestqueue.py
ignition/service/resourcedriver.py
ignition/service/templating.py
ignition/templates/__init__.py
ignition/templates/factory.py
ignition/templates/__pycache__/__init__.cpython-310.pyc
ignition/templates/__pycache__/factory.cpython-310.pyc
ignition/templates/driver_template/DESCRIPTION.md
ignition/templates/driver_template/MANIFEST.in
ignition/templates/driver_template/README.md
ignition/templates/driver_template/setup.py
ignition/templates/driver_template/devdocs/docker-image.md
ignition_framework-3.6.3.dist-info/LICENSE
ignition_framework-3.6.3.dist-info/METADATA
ignition_framework-3.6.3.dist-info/WHEEL
ignition_framework-3.6.3.dist-info/entry_points.txt
ignition_framework-3.6.3.dist-info/top_level.txt
ignition_framework-3.6.3.dist-info/RECORD
