Metadata-Version: 2.1
Name: ignition-framework
Version: 3.6.3
Summary: IBM CP4NA RM driver framework
Home-page: https://github.com/IBM/ignition
Author: IBM
Classifier: Programming Language :: Python :: 3
Classifier: License :: OSI Approved :: Apache Software License
Classifier: Operating System :: OS Independent
License-File: LICENSE
Requires-Dist: connexion[flask] ==3.0.6
Requires-Dist: kafka-python ==2.0.2
Requires-Dist: networkx ==2.5.1
Requires-Dist: frozendict ==2.0.2
Requires-Dist: Jinja2 ==3.1.4
Requires-Dist: requests ==2.32.3
Requires-Dist: click ==8.0.1
